pad/__init__.py
pad/app.py
pad/license.py
pad/pyarmor_runtime_011232/__init__.py
pad/pyarmor_runtime_011232/pyarmor_runtime.so
pad_app-0.3.3.dist-info/WHEEL
pad_app-0.3.3.dist-info/entry_points.txt
pad_app-0.3.3.dist-info/METADATA
pad_app-0.3.3.dist-info/RECORD
