Metadata-Version: 2.3
Name: pad-app
Version: 0.3.3
Summary: A terminal code editor for those of us who aren't into vim.
Author: Daniel Roy Greenfeld
Author-email: Daniel Roy Greenfeld <daniel@feldroy.com>
Requires-Dist: httpx>=0.28.0
Requires-Dist: textual[syntax]>=3.0.0
Requires-Dist: typer>=0.21.0
Requires-Dist: vexy-glob>=1.0.9
Requires-Python: >=3.14
